README.rst
setup.py
extensive_collection/__init__.py
extensive_collection/browser.py
extensive_collection/cleaners.py
extensive_collection/debug.py
extensive_collection/encoding.py
extensive_collection/htmls.py
extensive_collection/langdata.py
extensive_collection/readability.py
extensive_collection.egg-info/PKG-INFO
extensive_collection.egg-info/SOURCES.txt
extensive_collection.egg-info/dependency_links.txt
extensive_collection.egg-info/requires.txt
extensive_collection.egg-info/top_level.txt
extensive_collection/compat/__init__.py
extensive_collection/compat/three.py
extensive_collection/compat/two.py
extensive_collection/compat/__init__.py
extensive_collection/compat/three.py
extensive_collection/compat/two.py